hatch_version_action_example/__about__.py
hatch_version_action_example/__init__.py
hatch_version_action_example-0.1.1.dev3.dist-info/METADATA
hatch_version_action_example-0.1.1.dev3.dist-info/WHEEL
hatch_version_action_example-0.1.1.dev3.dist-info/licenses/LICENSE.txt
hatch_version_action_example-0.1.1.dev3.dist-info/RECORD
