Metadata-Version: 2.1
Name: hatch-version-action-example
Version: 0.1.1.dev3
Summary: An example project using hatch-version-action
Project-URL: Documentation, https://github.com/unknown/hatch-version-action-example#readme
Project-URL: Issues, https://github.com/unknown/hatch-version-action-example/issues
Project-URL: Source, https://github.com/unknown/hatch-version-action-example
Author-email: "Waylon S. Walker" <waylon@waylonwalker.com>
License-Expression: MIT
License-File: LICENSE.txt
Classifier: Development Status :: 4 - Beta
Classifier: Programming Language :: Python
Classifier: Programming Language :: Python :: 3.7
Classifier: Programming Language :: Python :: 3.8
Classifier: Programming Language :: Python :: 3.9
Classifier: Programming Language :: Python :: 3.10
Classifier: Programming Language :: Python :: 3.11
Classifier: Programming Language :: Python :: Implementation :: CPython
Classifier: Programming Language :: Python :: Implementation :: PyPy
Requires-Python: >=3.7
Provides-Extra: dev
Requires-Dist: black; extra == 'dev'
Requires-Dist: flake8; extra == 'dev'
Requires-Dist: isort; extra == 'dev'
Requires-Dist: pytest; extra == 'dev'
Requires-Dist: pytest-cov; extra == 'dev'
Requires-Dist: pytest-mock; extra == 'dev'
Requires-Dist: seed-isort-config; extra == 'dev'
